<?xml version="1.0" encoding="utf-16"?>
<AnnotationModel xmlns:xsd="http://www.w3.org/2001/XMLSchema" xmlns:xsi="http://www.w3.org/2001/XMLSchema-instance" Evalue="0" Width="29" Uid="BirA.1">
  <Sites>
    <regulon_site Name="PST_3866:-104" Site="AAACC---------------GGTTGACAG" Pvalue="2.08E-09" Start="5" Right="0" regulators="3558527" />
    <regulon_site Name="DvMF_1001:-91" Site="AACC----------------GGTTGACAA" Pvalue="3.47E-09" Start="6" Right="0" regulators="8500243" />
    <regulon_site Name="Glov_2370:-63" Site="AACC----------------GGTTGACAA" Pvalue="3.47E-09" Start="6" Right="0" regulators="7163749" />
    <regulon_site Name="CJA_0426:-63" Site="AACC----------------GGTTGACAG" Pvalue="8.5499999999999988E-09" Start="6" Right="0" regulators="5708618" />
    <regulon_site Name="Avin_05980:-139" Site="AACC----------------GGTTGACAG" Pvalue="8.5499999999999988E-09" Start="6" Right="0" regulators="6917051" />
    <regulon_site Name="plu1485:-86" Site="AACC----------------GGTTGACAG" Pvalue="8.5499999999999988E-09" Start="6" Right="0" regulators="552258" />
    <regulon_site Name="PSPTO0494:-128" Site="AACC----------------GGTTGACAG" Pvalue="8.5499999999999988E-09" Start="6" Right="0" regulators="333636" />
    <regulon_site Name="PFL_5693:-128" Site="AACC----------------GGTTGACAG" Pvalue="8.5499999999999988E-09" Start="6" Right="0" regulators="876237" />
    <regulon_site Name="Sde_3139:-90" Site="AACC----------------GGTTGACAG" Pvalue="8.5499999999999988E-09" Start="6" Right="0" regulators="3821275" />
    <regulon_site Name="DvMF_1000:-38" Site="AACC----------------GGTTTACAA" Pvalue="1.89E-08" Start="6" Right="0" regulators="8500243" />
    <regulon_site Name="PE36_13022:-32" Site="AACC----------------GGTTTACAA" Pvalue="1.89E-08" Start="6" Right="0" regulators="4633413" />
    <regulon_site Name="Avin_05970:-16" Site="AACC----------------GGTTTACAA" Pvalue="1.89E-08" Start="6" Right="0" regulators="6917051" />
    <regulon_site Name="Sde_3140:-33" Site="AACC----------------GGTTTACAA" Pvalue="1.89E-08" Start="6" Right="0" regulators="3821275" />
    <regulon_site Name="MELB17_06979:-102" Site="TAACC---------------GGTTGACAG" Pvalue="2.74E-08" Start="5" Right="0" regulators="4235739" />
    <regulon_site Name="Maqu_2756:-104" Site="TAACC---------------GGTTGACAG" Pvalue="2.74E-08" Start="5" Right="0" regulators="3522198" />
    <regulon_site Name="HCH_05371:-164" Site="TAACC---------------GGTTGACAG" Pvalue="2.74E-08" Start="5" Right="0" regulators="1098128" />
    <regulon_site Name="Dde_2655:-120" Site="AACC----------------AGTTGACAA" Pvalue="3.91E-08" Start="6" Right="0" regulators="394250" />
    <regulon_site Name="VAS14_01401:-213" Site="AACC----------------AGTTGACAG" Pvalue="7.63E-08" Start="6" Right="0" regulators="2795263" />
    <regulon_site Name="Sez_0191:-74" Site="AACC-----------------GTTGACAA" Pvalue="7.63E-08" Start="6" Right="1" regulators="5804210" />
    <regulon_site Name="PP0362:-127" Site="AACC----------------AGTTGACAG" Pvalue="7.63E-08" Start="6" Right="0" regulators="216139" />
    <regulon_site Name="Csal_1167:-102" Site="AACC----------------GGTTGACAT" Pvalue="7.63E-08" Start="6" Right="0" regulators="1811351" />
    <regulon_site Name="GM21_2164:-72" Site="CAACC---------------GGTTGACAA" Pvalue="1.04E-07" Start="5" Right="0" regulators="7318498" />
    <regulon_site Name="Geob_3008:-74" Site="CAACC---------------GGTTGACAA" Pvalue="1.04E-07" Start="5" Right="0" regulators="6906851" />
    <regulon_site Name="Gura_2242:-74" Site="CAACC---------------GGTTGACAA" Pvalue="1.04E-07" Start="5" Right="0" regulators="3528306" />
    <regulon_site Name="Gmet_1582:-75" Site="TAACC---------------AGTTGACAA" Pvalue="1.04E-07" Start="5" Right="0" regulators="1090498" />
    <regulon_site Name="TERTU_0489:-49" Site="AACC----------------AGTTTACAA" Pvalue="1.41E-07" Start="6" Right="0" regulators="7053670" />
    <regulon_site Name="MELB17_06979:-40" Site="AAACC---------------GGTTAACAG" Pvalue="1.41E-07" Start="5" Right="0" regulators="4235739" />
    <regulon_site Name="Maqu_2756:-41" Site="AAACC---------------GGTTAACAG" Pvalue="1.41E-07" Start="5" Right="0" regulators="3522198" />
    <regulon_site Name="GHTCC_010100004703:-44" Site="AACC----------------AGTTTACAA" Pvalue="1.41E-07" Start="6" Right="0" regulators="6223938" />
    <regulon_site Name="VSAL_II0861:-44" Site="AACC----------------AGTTTACAA" Pvalue="1.41E-07" Start="6" Right="0" regulators="5494783" />
    <regulon_site Name="EAM_1210:-80" Site="AACC----------------AGTTTACAA" Pvalue="1.41E-07" Start="6" Right="0" regulators="10476188" />
    <regulon_site Name="VF_A0748:-44" Site="AACC----------------AGTTTACAA" Pvalue="1.41E-07" Start="6" Right="0" regulators="945371" />
    <regulon_site Name="Mmwyl1_3457:-85" Site="AAACC---------------TGTTGACAG" Pvalue="1.89E-07" Start="5" Right="0" regulators="7177931" />
    <regulon_site Name="Pmen_4088:-119" Site="CAACC---------------GGTTGACAG" Pvalue="1.89E-07" Start="5" Right="0" regulators="3617180" />
    <regulon_site Name="DVU2558:-230" Site="AACC----------------CGTTGACAG" Pvalue="2.5000000000000004E-07" Start="6" Right="0" regulators="208054" />
    <regulon_site Name="Shewmr7_2431:-89" Site="AACC----------------CGTTGACAG" Pvalue="2.5000000000000004E-07" Start="6" Right="0" regulators="6867477" />
    <regulon_site Name="TERTU_0490:-110" Site="AACT----------------GGTTGACAA" Pvalue="2.5000000000000004E-07" Start="6" Right="0" regulators="7053670" />
    <regulon_site Name="GHTCC_010100004698:-92" Site="AACT----------------GGTTGACAA" Pvalue="2.5000000000000004E-07" Start="6" Right="0" regulators="6223938" />
    <regulon_site Name="Shewmr4_2359:-89" Site="AACC----------------CGTTGACAG" Pvalue="2.5000000000000004E-07" Start="6" Right="0" regulators="6863390" />
    <regulon_site Name="Shewana3_2519:-89" Site="AACC----------------CGTTGACAG" Pvalue="2.5000000000000004E-07" Start="6" Right="0" regulators="7022938" />
    <regulon_site Name="PSPTO0493:5" Site="AACC----------------GGTTTACAT" Pvalue="2.5000000000000004E-07" Start="6" Right="0" regulators="333636" />
    <regulon_site Name="PFL_5694:5" Site="AACC----------------GGTTTACAT" Pvalue="2.5000000000000004E-07" Start="6" Right="0" regulators="876237" />
    <regulon_site Name="Swoo_1866:-99" Site="AACC----------------CGTTGACAG" Pvalue="2.5000000000000004E-07" Start="6" Right="0" regulators="7103076" />
    <regulon_site Name="Ssed_2776:-99" Site="AACC----------------CGTTGACAG" Pvalue="2.5000000000000004E-07" Start="6" Right="0" regulators="3703484" />
    <regulon_site Name="Shew_1719:-122" Site="AACC----------------CGTTGACAG" Pvalue="2.5000000000000004E-07" Start="6" Right="0" regulators="5207613" />
    <regulon_site Name="Sama_1438:-86" Site="AACC----------------CGTTGACAG" Pvalue="2.5000000000000004E-07" Start="6" Right="0" regulators="6935988" />
    <regulon_site Name="SO_2740:-89" Site="AACC----------------CGTTGACAG" Pvalue="2.5000000000000004E-07" Start="6" Right="0" regulators="199409" />
    <regulon_site Name="PST_3867:-21" Site="CAACC---------------GGTTTACAA" Pvalue="3.2600000000000003E-07" Start="5" Right="0" regulators="3558527" />
    <regulon_site Name="smi_0834:-87" Site="TACC-----------------GTTGACAA" Pvalue="4.23E-07" Start="6" Right="1" regulators="10162203" />
    <regulon_site Name="SDEG_1997:-73" Site="TACC-----------------GTTGACAA" Pvalue="4.23E-07" Start="6" Right="1" regulators="7472955" />
    <regulon_site Name="VSAL_II0860:-95" Site="AACT----------------GGTTGACAG" Pvalue="4.23E-07" Start="6" Right="0" regulators="5494783" />
    <regulon_site Name="VC1112:-93" Site="AACC----------------TGTTGACAG" Pvalue="4.23E-07" Start="6" Right="0" regulators="52929" />
    <regulon_site Name="SPy0205:-73" Site="TACC-----------------GTTGACAA" Pvalue="4.23E-07" Start="6" Right="1" regulators="101612" />
    <regulon_site Name="VF_A1189:-117" Site="AACT----------------GGTTGACAG" Pvalue="4.23E-07" Start="6" Right="0" regulators="945371" />
    <regulon_site Name="DVU2557:-38" Site="AACG----------------GGTTTACAA" Pvalue="5.4200000000000006E-07" Start="6" Right="0" regulators="208054" />
    <regulon_site Name="RED65_04570:-152" Site="AAACC---------------GGTTGACTG" Pvalue="5.4200000000000006E-07" Start="5" Right="0" regulators="2916188" />
    <regulon_site Name="GSU1584:-79" Site="CAACC---------------AGTTGACAA" Pvalue="5.4200000000000006E-07" Start="5" Right="0" regulators="382234" />
    <regulon_site Name="Dde_2654:-21" Site="AACT----------------GGTTTACAA" Pvalue="6.8900000000000009E-07" Start="6" Right="0" regulators="394250" />
    <regulon_site Name="EAM_1209:-41" Site="AACT----------------GGTTTACAA" Pvalue="6.8900000000000009E-07" Start="6" Right="0" regulators="10476188" />
    <regulon_site Name="PP0361:5" Site="AACT----------------GGTTTACAA" Pvalue="6.8900000000000009E-07" Start="6" Right="0" regulators="216139" />
    <regulon_site Name="OB1717:-81" Site="TAAAC----------------GTTGACAA" Pvalue="1.09E-06" Start="4" Right="0" regulators="278546" />
    <regulon_site Name="ABC0344:-87" Site="TAAAC----------------GTTGACAA" Pvalue="1.09E-06" Start="4" Right="0" regulators="823554" />
    <regulon_site Name="BC3629:-111" Site="TAAAC----------------GTTGACAA" Pvalue="1.09E-06" Start="4" Right="0" regulators="358854" />
    <regulon_site Name="GK3018:-84" Site="TAAAC----------------GTTGACAA" Pvalue="1.09E-06" Start="4" Right="0" regulators="854051" />
    <regulon_site Name="GK1570:-86" Site="TAAAC----------------GTTGACAA" Pvalue="1.09E-06" Start="4" Right="0" regulators="854051" />
    <regulon_site Name="RBAM_029080:-84" Site="TAAAC----------------GTTGACAA" Pvalue="1.09E-06" Start="4" Right="0" regulators="3456436" />
    <regulon_site Name="Smlt4459:-91" Site="ACC-----------------GGTTGACAG" Pvalue="1.09E-06" Start="7" Right="0" regulators="5775629" />
    <regulon_site Name="Spro_1311:-88" Site="ACC-----------------GGTTGACAG" Pvalue="1.09E-06" Start="7" Right="0" regulators="3618219" />
    <regulon_site Name="ECA2825:-86" Site="ACC-----------------GGTTGACAG" Pvalue="1.09E-06" Start="7" Right="0" regulators="604568" />
    <regulon_site Name="y3031:-89" Site="ACC-----------------GGTTGACAG" Pvalue="1.09E-06" Start="7" Right="0" regulators="271032" />
    <regulon_site Name="CPS_2594:-87" Site="AACC----------------CGTTGACAT" Pvalue="1.09E-06" Start="6" Right="0" regulators="842552" />
    <regulon_site Name="Mmwyl1_3458:15" Site="CAACA---------------GGTTTACAA" Pvalue="1.35E-06" Start="5" Right="0" regulators="7177931" />
    <regulon_site Name="VC1111:-66" Site="AACA----------------GGTTTACAT" Pvalue="1.35E-06" Start="6" Right="0" regulators="52929" />
    <regulon_site Name="KPN_00800:-230" Site="ACC-----------------GGTTTACAA" Pvalue="1.67E-06" Start="7" Right="0" regulators="3384828" />
    <regulon_site Name="KPN_00799:-41" Site="ACC-----------------GGTTTACAA" Pvalue="1.67E-06" Start="7" Right="0" regulators="3384828" />
    <regulon_site Name="CKO_02354:-41" Site="ACC-----------------GGTTTACAA" Pvalue="1.67E-06" Start="7" Right="0" regulators="3404687" />
    <regulon_site Name="CJA_0425:-147" Site="AACC----------------GGTTTACTA" Pvalue="1.67E-06" Start="6" Right="0" regulators="5708618" />
    <regulon_site Name="Spro_1310:-17" Site="ACC-----------------GGTTTACAA" Pvalue="1.67E-06" Start="7" Right="0" regulators="3618219" />
    <regulon_site Name="STM0793:-41" Site="ACC-----------------GGTTTACAA" Pvalue="1.67E-06" Start="7" Right="0" regulators="151393" />
    <regulon_site Name="Ent638_1265:-22" Site="ACC-----------------GGTTTACAA" Pvalue="1.67E-06" Start="7" Right="0" regulators="3627111" />
    <regulon_site Name="b0775:-79" Site="ACC-----------------GGTTTACAA" Pvalue="1.67E-06" Start="7" Right="0" regulators="18008" />
    <regulon_site Name="b0774:-41" Site="ACC-----------------GGTTTACAA" Pvalue="1.67E-06" Start="7" Right="0" regulators="18008" />
    <regulon_site Name="y3032:-43" Site="ACC-----------------GGTTTACAA" Pvalue="1.67E-06" Start="7" Right="0" regulators="271032" />
    <regulon_site Name="Pcar_1666:-62" Site="CAACC---------------TGTTGACAA" Pvalue="2.05E-06" Start="5" Right="0" regulators="1910840" />
    <regulon_site Name="Pcar_1458:-137" Site="CAACC---------------TGTTGACAA" Pvalue="2.05E-06" Start="5" Right="0" regulators="1910840" />
    <regulon_site Name="SAG0464:-78" Site="TAAC-----------------GTTTACAA" Pvalue="2.05E-06" Start="6" Right="1" regulators="275466" />
    <regulon_site Name="MELB17_06974:21" Site="CAACC---------------GGTTAACAG" Pvalue="2.49E-06" Start="5" Right="0" regulators="4235739" />
    <regulon_site Name="GK3098:-330" Site="TAAAC----------------GTTTACAA" Pvalue="2.49E-06" Start="4" Right="0" regulators="854051" />
    <regulon_site Name="Aflv_1163:-45" Site="TAAAC----------------GTTTACAA" Pvalue="2.49E-06" Start="4" Right="0" regulators="5699981" />
    <regulon_site Name="Maqu_2757:21" Site="CAACC---------------GGTTAACAG" Pvalue="2.49E-06" Start="5" Right="0" regulators="3522198" />
    <regulon_site Name="ETAE_2555:-141" Site="ACC-----------------GGTTTACAG" Pvalue="2.49E-06" Start="7" Right="0" regulators="10254009" />
    <regulon_site Name="SAG0465:-79" Site="AAAC-----------------GTTAACAA" Pvalue="2.49E-06" Start="6" Right="1" regulators="275466" />
    <regulon_site Name="Ping_1924:-249" Site="AAAGA---------------AGTTGACAG" Pvalue="2.49E-06" Start="5" Right="0" regulators="1972654" />
    <regulon_site Name="HCH_05372:30" Site="CAACC---------------GGTTAACAG" Pvalue="2.49E-06" Start="5" Right="0" regulators="1098128" />
    <regulon_site Name="SP_0783:-87" Site="TACC-----------------GTTGACAT" Pvalue="2.49E-06" Start="6" Right="1" regulators="117330" />
    <regulon_site Name="CPS_2593:-33" Site="AACG----------------GGTTAACAA" Pvalue="2.49E-06" Start="6" Right="0" regulators="842552" />
    <regulon_site Name="Glov_1662:-32" Site="AACT----------------GGTTAACAA" Pvalue="3.02E-06" Start="6" Right="0" regulators="7163749" />
    <regulon_site Name="Sbal_1758:-89" Site="AACT----------------CGTTGACAG" Pvalue="3.63E-06" Start="6" Right="0" regulators="6935564" />
    <regulon_site Name="Geob_2084:-90" Site="TAACC---------------GGTTGACGA" Pvalue="3.63E-06" Start="5" Right="0" regulators="6906851" />
    <regulon_site Name="Gura_3246:-94" Site="TAACC---------------GGTTGACGA" Pvalue="3.63E-06" Start="5" Right="0" regulators="3528306" />
    <regulon_site Name="MELB17_04752:-78" Site="TAACT---------------GGTTAACAG" Pvalue="3.63E-06" Start="5" Right="0" regulators="4235739" />
    <regulon_site Name="PCNPT3_07375:-97" Site="AAAGT---------------AGTTGACAG" Pvalue="3.63E-06" Start="5" Right="0" regulators="2859627" />
    <regulon_site Name="VAS14_01396:-35" Site="AACT----------------GGTTTACAT" Pvalue="3.63E-06" Start="6" Right="0" regulators="2795263" />
    <regulon_site Name="ETAE_2554:-94" Site="ACC-----------------GGTTGACAT" Pvalue="3.63E-06" Start="7" Right="0" regulators="10254009" />
    <regulon_site Name="XAC0388:-93" Site="ACC-----------------AGTTGACAG" Pvalue="3.63E-06" Start="7" Right="0" regulators="259863" />
    <regulon_site Name="XCC0388:-93" Site="ACC-----------------AGTTGACAG" Pvalue="3.63E-06" Start="7" Right="0" regulators="255218" />
    <regulon_site Name="Sputw3181_1663:-90" Site="AACT----------------CGTTGACAG" Pvalue="3.63E-06" Start="6" Right="0" regulators="6977999" />
    <regulon_site Name="Sputcn32_2345:-90" Site="AACT----------------CGTTGACAG" Pvalue="3.63E-06" Start="6" Right="0" regulators="3440527" />
    <regulon_site Name="OB2346:-81" Site="TCAAC----------------GTTGACAA" Pvalue="5.16E-06" Start="4" Right="0" regulators="278546" />
    <regulon_site Name="BH3358:-87" Site="TCAAC----------------GTTGACAA" Pvalue="5.16E-06" Start="4" Right="0" regulators="64266" />
    <regulon_site Name="BC3629:-46" Site="TTACC----------------GTTTACAA" Pvalue="5.16E-06" Start="4" Right="0" regulators="358854" />
    <regulon_site Name="BSU10370:-88" Site="TAAAC----------------GTTGACAT" Pvalue="5.16E-06" Start="4" Right="0" regulators="38781" />
    <regulon_site Name="VSAK1_00085:-91" Site="AACT----------------TGTTGACAG" Pvalue="5.16E-06" Start="6" Right="0" regulators="4609093" />
    <regulon_site Name="LSL_0074:-91" Site="TAAC-----------------GTTAACAA" Pvalue="7.19E-06" Start="6" Right="1" regulators="1254893" />
    <regulon_site Name="OEOE_1596:-48" Site="TAAC-----------------GTTAACAA" Pvalue="7.19E-06" Start="6" Right="1" regulators="2183042" />
    <regulon_site Name="ABC2607:-82" Site="TTAAC----------------GTTGACAA" Pvalue="8.42E-06" Start="4" Right="0" regulators="823554" />
    <regulon_site Name="Aflv_1070:-52" Site="TTAAC----------------GTTGACAA" Pvalue="8.42E-06" Start="4" Right="0" regulators="5699981" />
    <regulon_site Name="BLi03385:-89" Site="TTAAC----------------GTTGACAA" Pvalue="8.42E-06" Start="4" Right="0" regulators="728384" />
    <regulon_site Name="BPUM_2863:-83" Site="TTAAC----------------GTTGACAA" Pvalue="8.42E-06" Start="4" Right="0" regulators="3426889" />
    <regulon_site Name="BSU32030:-87" Site="TTAAC----------------GTTGACAA" Pvalue="8.42E-06" Start="4" Right="0" regulators="38781" />
    <regulon_site Name="SAG0397:-72" Site="TTAAC----------------GTTGACAA" Pvalue="8.42E-06" Start="5" Right="1" regulators="275466" />
    <regulon_site Name="GM21_3430:-102" Site="CAACC---------------GGTTGACGA" Pvalue="9.8100000000000009E-06" Start="5" Right="0" regulators="7318498" />
    <regulon_site Name="MELB17_06974:-41" Site="TAACC---------------GGTTTACGG" Pvalue="9.8100000000000009E-06" Start="5" Right="0" regulators="4235739" />
    <regulon_site Name="GK2128:-46" Site="TAAAC----------------GTTTACAT" Pvalue="9.8100000000000009E-06" Start="4" Right="0" regulators="854051" />
    <regulon_site Name="Maqu_2757:-42" Site="TAACC---------------GGTTTACGG" Pvalue="9.8100000000000009E-06" Start="5" Right="0" regulators="3522198" />
    <regulon_site Name="PMI0603:-85" Site="ACC-----------------AGTTGACAT" Pvalue="9.8100000000000009E-06" Start="7" Right="0" regulators="5785362" />
    <regulon_site Name="Pmen_4089:-107" Site="CAACC---------------GGTTGACGA" Pvalue="9.8100000000000009E-06" Start="5" Right="0" regulators="3617180" />
    <regulon_site Name="GSU2629:-87" Site="CAACC---------------GGTTGACGA" Pvalue="9.8100000000000009E-06" Start="5" Right="0" regulators="382234" />
    <regulon_site Name="Gmet_0842:-65" Site="CAACC---------------GGTTGACGA" Pvalue="9.8100000000000009E-06" Start="5" Right="0" regulators="1090498" />
    <regulon_site Name="PE36_13017:-92" Site="AACC----------------GGTTGACCT" Pvalue="1.14E-05" Start="6" Right="0" regulators="4633413" />
    <regulon_site Name="LEUM_0516:-45" Site="AAAC-----------------GTTTACTA" Pvalue="1.14E-05" Start="6" Right="1" regulators="2179849 2180055" />
    <regulon_site Name="Swoo_1865:-44" Site="AACG----------------GGTTTACTA" Pvalue="1.14E-05" Start="6" Right="0" regulators="7103076" />
    <regulon_site Name="Ssed_2777:-44" Site="AACG----------------GGTTTACTA" Pvalue="1.14E-05" Start="6" Right="0" regulators="3703484" />
    <regulon_site Name="Shew_1718:-60" Site="AACG----------------GGTTTACTA" Pvalue="1.14E-05" Start="6" Right="0" regulators="5207613" />
    <regulon_site Name="GALLO_2102:-69" Site="TAAC-----------------GTTGACTA" Pvalue="1.52E-05" Start="6" Right="1" regulators="10395465" />
    <regulon_site Name="BH1748:-56" Site="TTAAC----------------GTTTACAA" Pvalue="1.52E-05" Start="4" Right="0" regulators="64266" />
    <regulon_site Name="ABO_2220:-83" Site="ACT-----------------GGTTGACAG" Pvalue="1.52E-05" Start="7" Right="0" regulators="2080038" />
    <regulon_site Name="str0674:-89" Site="TAAC-----------------GTTGACTA" Pvalue="1.52E-05" Start="6" Right="1" regulators="927322" />
    <regulon_site Name="plu1484:-41" Site="AACC----------------GGTTTACGT" Pvalue="1.52E-05" Start="6" Right="0" regulators="552258" />
    <regulon_site Name="Sama_1437:-57" Site="AACG----------------GGTTTACTG" Pvalue="1.52E-05" Start="6" Right="0" regulators="6935988" />
    <regulon_site Name="Mmol_0572:-118" Site="CAAA----------------TGTTGACAA" Pvalue="1.74E-05" Start="6" Right="0" regulators="7670863" />
    <regulon_site Name="SSA_1536:-36" Site="TACC-----------------GTTTACTA" Pvalue="1.74E-05" Start="6" Right="1" regulators="2060542" />
    <regulon_site Name="SGO_0746:-35" Site="TACC-----------------GTTTACTA" Pvalue="1.74E-05" Start="6" Right="1" regulators="3789217" />
    <regulon_site Name="Sfri_1475:-87" Site="AAGC----------------CGTTGACAG" Pvalue="1.99E-05" Start="6" Right="0" regulators="6912386" />
    <regulon_site Name="BC4917:107" Site="TAAC-----------------GTTAACAT" Pvalue="2.26E-05" Start="5" Right="0" regulators="358854" />
    <regulon_site Name="LAR_0704:-71" Site="AACC-----------------GGTTACAA" Pvalue="2.26E-05" Start="6" Right="1" regulators="5813715" />
    <regulon_site Name="LAF_0321:-54" Site="AACC-----------------GGTTACAA" Pvalue="2.26E-05" Start="6" Right="1" regulators="5502787" />
    <regulon_site Name="str1308:-171" Site="TAAC-----------------GTTAACAT" Pvalue="2.26E-05" Start="6" Right="1" regulators="927322" />
    <regulon_site Name="Sbal_1757:-66" Site="AACG----------------AGTTTACTA" Pvalue="2.5699999999999998E-05" Start="6" Right="0" regulators="6935564" />
    <regulon_site Name="Aflv_1376:-55" Site="TTAAC----------------GTTGACAT" Pvalue="2.5699999999999998E-05" Start="4" Right="0" regulators="5699981" />
    <regulon_site Name="BPUM_2376:-88" Site="TTAAC----------------GTTGACAT" Pvalue="2.5699999999999998E-05" Start="4" Right="0" regulators="3426889" />
    <regulon_site Name="RBAM_010550:-87" Site="TTAAC----------------GTTGACAT" Pvalue="2.5699999999999998E-05" Start="4" Right="0" regulators="3456436" />
    <regulon_site Name="RBAM_018290:-126" Site="TTAAC----------------GTTGACAT" Pvalue="2.5699999999999998E-05" Start="4" Right="0" regulators="3456436" />
    <regulon_site Name="PTD2_19562:-34" Site="ACA-----------------AGTTTACAT" Pvalue="2.5699999999999998E-05" Start="7" Right="0" regulators="2786991" />
    <regulon_site Name="VS_2041:-72" Site="ACA-----------------AGTTTACAT" Pvalue="2.5699999999999998E-05" Start="7" Right="0" regulators="5239933" />
    <regulon_site Name="VIBHAR_01806:-73" Site="ACA-----------------AGTTTACAT" Pvalue="2.5699999999999998E-05" Start="7" Right="0" regulators="3480950" />
    <regulon_site Name="XAC0389:16" Site="ACT-----------------GGTTTACAG" Pvalue="2.5699999999999998E-05" Start="7" Right="0" regulators="259863" />
    <regulon_site Name="XCC0389:16" Site="ACT-----------------GGTTTACAG" Pvalue="2.5699999999999998E-05" Start="7" Right="0" regulators="255218" />
    <regulon_site Name="VP1112:-73" Site="ACA-----------------AGTTTACAT" Pvalue="2.5699999999999998E-05" Start="7" Right="0" regulators="341443" />
    <regulon_site Name="VV1_2944:-72" Site="ACA-----------------AGTTTACAT" Pvalue="2.5699999999999998E-05" Start="7" Right="0" regulators="309369" />
    <regulon_site Name="L24742:-79" Site="AACC-----------------GTTAACTG" Pvalue="2.5699999999999998E-05" Start="6" Right="1" regulators="78589" />
    <regulon_site Name="Sputw3181_1662:-66" Site="AACG----------------AGTTTACTA" Pvalue="2.5699999999999998E-05" Start="6" Right="0" regulators="6977999" />
    <regulon_site Name="PSEEN5121:-127" Site="AGCC----------------GGTTGACAG" Pvalue="2.5699999999999998E-05" Start="6" Right="0" regulators="2046699" />
    <regulon_site Name="LACR_1954:-136" Site="AACC-----------------GTTAACTG" Pvalue="2.5699999999999998E-05" Start="6" Right="1" regulators="1789226" />
    <regulon_site Name="Sputcn32_2346:-66" Site="AACG----------------AGTTTACTA" Pvalue="2.5699999999999998E-05" Start="6" Right="0" regulators="3440527" />
    <regulon_site Name="Shewmr7_2432:-66" Site="AACG----------------GGTTTACCA" Pvalue="2.91E-05" Start="6" Right="0" regulators="6867477" />
    <regulon_site Name="Shewmr4_2360:-66" Site="AACG----------------GGTTTACCA" Pvalue="2.91E-05" Start="6" Right="0" regulators="6863390" />
    <regulon_site Name="Shewana3_2520:-66" Site="AACG----------------GGTTTACCA" Pvalue="2.91E-05" Start="6" Right="0" regulators="7022938" />
    <regulon_site Name="Csal_1167:-46" Site="CAACC---------------AGTTGACCA" Pvalue="2.91E-05" Start="5" Right="0" regulators="1811351" />
    <regulon_site Name="swp_2928:-242" Site="AACC----------------CATTGACAG" Pvalue="2.91E-05" Start="6" Right="0" regulators="5434615" />
    <regulon_site Name="Shal_2477:-236" Site="AACC----------------CATTGACAG" Pvalue="2.91E-05" Start="6" Right="0" regulators="3788142" />
    <regulon_site Name="Spea_1801:-238" Site="AACC----------------CATTGACAG" Pvalue="2.91E-05" Start="6" Right="0" regulators="7158160" />
    <regulon_site Name="SO_2741:-66" Site="AACG----------------GGTTTACCA" Pvalue="2.91E-05" Start="6" Right="0" regulators="199409" />
    <regulon_site Name="SE0234:-110" Site="GTAAACTTATAAATATATAAAGTTTACAA" Pvalue="3.28E-05" Start="4" Right="1" regulators="313936" />
    <regulon_site Name="Ppro_2093:-42" Site="CAACT---------------GGTTGACCA" Pvalue="3.6899999999999996E-05" Start="5" Right="0" regulators="1912977" />
    <regulon_site Name="BH3907:-66" Site="TTAAC----------------GTTAACAA" Pvalue="3.6899999999999996E-05" Start="4" Right="0" regulators="64266" />
    <regulon_site Name="Aflv_2398:-31" Site="TTAAC----------------GTTAACAA" Pvalue="3.6899999999999996E-05" Start="4" Right="0" regulators="5699981" />
    <regulon_site Name="BSU30240:-85" Site="TTAAC----------------GTTAACAA" Pvalue="3.6899999999999996E-05" Start="4" Right="0" regulators="38781" />
    <regulon_site Name="PBPRA2329:-149" Site="AACC----------------TATTGACAG" Pvalue="3.6899999999999996E-05" Start="6" Right="0" regulators="775163" />
    <regulon_site Name="MADE_02211:-86" Site="AAGG----------------AGTTGACAA" Pvalue="3.6899999999999996E-05" Start="6" Right="0" regulators="6897924" />
    <regulon_site Name="SDEG_0560:-32" Site="TAAC-----------------GGTGACAA" Pvalue="4.13E-05" Start="6" Right="1" regulators="7472955" />
    <regulon_site Name="ATW7_13073:-95" Site="ACT-----------------CGTTGACAA" Pvalue="4.13E-05" Start="7" Right="0" regulators="3135491" />
    <regulon_site Name="GK2944:-31" Site="TTAAC----------------GTTTACAT" Pvalue="4.13E-05" Start="4" Right="0" regulators="854051" />
    <regulon_site Name="CKO_02353:-79" Site="ACC-----------------GGTTTACGA" Pvalue="4.13E-05" Start="7" Right="0" regulators="3404687" />
    <regulon_site Name="ECA2826:-43" Site="ACC-----------------GGTTTACGA" Pvalue="4.13E-05" Start="7" Right="0" regulators="604568" />
    <regulon_site Name="STM0794:-79" Site="ACC-----------------GGTTTACGA" Pvalue="4.13E-05" Start="7" Right="0" regulators="151393" />
    <regulon_site Name="SA2077:-75" Site="GTAAACTTTTCATTTCTTAAAGTTTACAA" Pvalue="4.13E-05" Start="4" Right="1" regulators="103596" />
    <regulon_site Name="PSHAa1609:-99" Site="ACT-----------------CGTTGACAA" Pvalue="4.13E-05" Start="7" Right="0" regulators="1131664" />
    <regulon_site Name="Patl_2557:-87" Site="AAGT----------------AGTTGACAA" Pvalue="4.13E-05" Start="6" Right="0" regulators="3503867" />
    <regulon_site Name="SE1856:-70" Site="GTAAACTTTCCATTCATAAAAGTTTACAA" Pvalue="4.63E-05" Start="4" Right="1" regulators="313936" />
    <regulon_site Name="PTD2_19567:-95" Site="ACT-----------------TGTTGACAA" Pvalue="5.1699999999999996E-05" Start="7" Right="0" regulators="2786991" />
    <regulon_site Name="PMI0602:-52" Site="ACT-----------------GGTTTACAT" Pvalue="5.1699999999999996E-05" Start="7" Right="0" regulators="5785362" />
    <regulon_site Name="Ent638_1266:-79" Site="ACC-----------------GGTTTACCA" Pvalue="5.1699999999999996E-05" Start="7" Right="0" regulators="3627111" />
    <regulon_site Name="SUB1710:-61" Site="TACC-----------------GTTGACAC" Pvalue="5.1699999999999996E-05" Start="6" Right="1" regulators="5936454" />
    <regulon_site Name="GALLO_1527:-52" Site="TAAC-----------------GTTAACTA" Pvalue="5.7499999999999995E-05" Start="6" Right="1" regulators="10395465" />
    <regulon_site Name="ABO_2221:4" Site="ACC-----------------AGTTTACTG" Pvalue="5.7499999999999995E-05" Start="7" Right="0" regulators="2080038" />
    <regulon_site Name="SMU.1827:-48" Site="TAAC-----------------GTTAACTA" Pvalue="5.7499999999999995E-05" Start="6" Right="1" regulators="296265" />
    <regulon_site Name="lp_0854:-55" Site="TAAC-----------------GTTAACTA" Pvalue="5.7499999999999995E-05" Start="6" Right="1" regulators="329946 329507" />
    <regulon_site Name="Pjdr2_1461:40" Site="AC-------------------GTTAACAA" Pvalue="6.39E-05" Start="7" Right="0" regulators="6924198" />
    <regulon_site Name="VS_2040:-121" Site="ACT-----------------TGTTGACAG" Pvalue="6.39E-05" Start="7" Right="0" regulators="5239933" />
    <regulon_site Name="VIBHAR_01807:-73" Site="ACT-----------------TGTTGACAG" Pvalue="6.39E-05" Start="7" Right="0" regulators="3480950" />
    <regulon_site Name="VP1113:-90" Site="ACT-----------------TGTTGACAG" Pvalue="6.39E-05" Start="7" Right="0" regulators="341443" />
    <regulon_site Name="VV1_2943:-102" Site="ACT-----------------TGTTGACAG" Pvalue="6.39E-05" Start="7" Right="0" regulators="309369" />
    <regulon_site Name="Sez_1400:-32" Site="TAAC-----------------GGTTACAA" Pvalue="6.39E-05" Start="6" Right="1" regulators="5804210" />
    <regulon_site Name="GALLO_1916:-51" Site="TAAC-----------------GTTAACTG" Pvalue="7.09E-05" Start="6" Right="1" regulators="10395465" />
    <regulon_site Name="SDEG_0379:-50" Site="AAAC-----------------GGTAACAA" Pvalue="7.09E-05" Start="6" Right="1" regulators="7472955" />
    <regulon_site Name="VSAK1_00080:-62" Site="AACA----------------AGTTTACAC" Pvalue="7.09E-05" Start="6" Right="0" regulators="4609093" />
    <regulon_site Name="PA0500:-129" Site="AGTCC---------------GGTTGACAG" Pvalue="7.09E-05" Start="5" Right="0" regulators="60730" />
    <regulon_site Name="swp_2929:-44" Site="AATG----------------GGTTTACTA" Pvalue="7.09E-05" Start="6" Right="0" regulators="5434615" />
    <regulon_site Name="Shal_2478:-44" Site="AATG----------------GGTTTACTA" Pvalue="7.09E-05" Start="6" Right="0" regulators="3788142" />
    <regulon_site Name="Spea_1800:-44" Site="AATG----------------GGTTTACTA" Pvalue="7.09E-05" Start="6" Right="0" regulators="7158160" />
    <regulon_site Name="Sden_1658:-86" Site="AAGT----------------CGTTGACAG" Pvalue="7.85E-05" Start="6" Right="0" regulators="6908498" />
    <regulon_site Name="SSP0625:-67" Site="GTAAACTTTTTATTTTTTAAAGTTTACAT" Pvalue="7.85E-05" Start="4" Right="1" regulators="920973" />
    <regulon_site Name="SH0770:-69" Site="GTAAACTTTTTATTTTATAAAGTTTACAT" Pvalue="7.85E-05" Start="4" Right="1" regulators="918387" />
    <regulon_site Name="Sca_2225:-73" Site="GTAAACTTATAAAAATTAAAAGTTTACAT" Pvalue="7.85E-05" Start="4" Right="1" regulators="5567253" />
    <regulon_site Name="STACA0001_0034:-87" Site="GTAAACTTATAAATATATAAAGTTTACAT" Pvalue="7.85E-05" Start="4" Right="1" regulators="6431619" />
    <regulon_site Name="SA2215:-55" Site="GTAAACTTATTAATTATAAAAGTTTACAT" Pvalue="7.85E-05" Start="4" Right="1" regulators="103596" />
    <regulon_site Name="BH0783:-42" Site="TTAAC----------------GTTAACAT" Pvalue="8.68E-05" Start="4" Right="0" regulators="64266" />
    <regulon_site Name="BC4119:-45" Site="TTAAC----------------GTTAACAT" Pvalue="8.68E-05" Start="4" Right="0" regulators="358854" />
    <regulon_site Name="BLi00766:-55" Site="TTAAC----------------GTTAACAT" Pvalue="8.68E-05" Start="4" Right="0" regulators="728384" />
    <regulon_site Name="BPUM_2779:-48" Site="TTAAC----------------GTTAACAT" Pvalue="8.68E-05" Start="4" Right="0" regulators="3426889" />
    <regulon_site Name="RBAM_018290:-64" Site="TTAAC----------------GTTAACAT" Pvalue="8.68E-05" Start="4" Right="0" regulators="3456436" />
    <regulon_site Name="ASA_2877:-181" Site="ATT-----------------TGTTGACAG" Pvalue="8.68E-05" Start="7" Right="0" regulators="3564095" />
    <regulon_site Name="AHA_1489:-180" Site="ATT-----------------TGTTGACAG" Pvalue="8.68E-05" Start="7" Right="0" regulators="2035694" />
    <regulon_site Name="SH0269:-75" Site="GTAAACTTATTTATATATAAAGTTTACAT" Pvalue="8.68E-05" Start="4" Right="1" regulators="918387" />
    <regulon_site Name="STACA0001_1211:-70" Site="GTAAACTTTTTATTTCTTAAAGTTTACAT" Pvalue="8.68E-05" Start="4" Right="1" regulators="6431619" />
    <regulon_site Name="CV4382:-39" Site="CAAAC---------------AATTGACAA" Pvalue="8.68E-05" Start="5" Right="0" regulators="515647" />
    <regulon_site Name="Patl_2558:-44" Site="AACT----------------ACTTTACAA" Pvalue="8.68E-05" Start="6" Right="0" regulators="3503867" />
    <regulon_site Name="Sca_1775:-75" Site="GTAAACTTTTAGTAAATTCAAGTTAACAA" Pvalue="9.57E-05" Start="4" Right="1" regulators="5567253" />
    <regulon_site Name="PSEEN5122:5" Site="AACC----------------GGCTTACAA" Pvalue="9.57E-05" Start="6" Right="0" regulators="2046699" />
    <regulon_site Name="Tola_1097:-90" Site="AATA----------------GATTGACAG" Pvalue="0.00010499999999999999" Start="6" Right="0" regulators="7700874" />
    <regulon_site Name="SPy0524:-269" Site="CACC-----------------GGTTACAG" Pvalue="0.00010499999999999999" Start="6" Right="1" regulators="101612" />
    <regulon_site Name="SE0344:-44" Site="GTAAACATAATTATATAAAGTGTTTACAA" Pvalue="0.00010499999999999999" Start="4" Right="1" regulators="313936" />
    <regulon_site Name="SE0179:-55" Site="GTAAACTTTAAAATGTAATAAGTTTACAT" Pvalue="0.00010499999999999999" Start="4" Right="1" regulators="313936" />
    <regulon_site Name="ASA_2878:-45" Site="ACA-----------------AATTGACAA" Pvalue="0.000116" Start="7" Right="0" regulators="3564095" />
    <regulon_site Name="AHA_1488:145" Site="ACA-----------------AATTGACAA" Pvalue="0.000116" Start="7" Right="0" regulators="2035694" />
    <regulon_site Name="Mfla_2164:-469" Site="AATG----------------GCTTGACAA" Pvalue="0.000127" Start="6" Right="0" regulators="1767979" />
    <regulon_site Name="PEPE_1637:-81" Site="AACC-----------------GGTTACTA" Pvalue="0.000127" Start="6" Right="1" regulators="1795304" />
    <regulon_site Name="Pjdr2_3366:-158" Site="AC-------------------GTTAACAT" Pvalue="0.000139" Start="7" Right="0" regulators="6924198" />
    <regulon_site Name="smi_0834:-35" Site="TACT-----------------GTTAACTA" Pvalue="0.000139" Start="6" Right="1" regulators="10162203" />
    <regulon_site Name="PCNPT3_07370:-43" Site="CAACT---------------ACTTTACAA" Pvalue="0.000139" Start="5" Right="0" regulators="2859627" />
    <regulon_site Name="SP_0783:-35" Site="TACT-----------------GTTAACTA" Pvalue="0.000139" Start="6" Right="1" regulators="117330" />
    <regulon_site Name="lp_0336:-76" Site="AACC-----------------GGTTACTG" Pvalue="0.000153" Start="6" Right="1" regulators="329946 329507" />
    <regulon_site Name="lp_0854:-158" Site="ACAC-----------------GGTTACAT" Pvalue="0.000167" Start="6" Right="1" regulators="329946 329507" />
    <regulon_site Name="Nmul_A1129:-164" Site="TCAAA---------------AATTGACAA" Pvalue="0.00018199999999999998" Start="5" Right="0" regulators="1125805" />
    <regulon_site Name="Sfri_1474:-60" Site="AACG----------------GCTTTACTA" Pvalue="0.00019899999999999999" Start="6" Right="0" regulators="6912386" />
    <regulon_site Name="ATW7_13078:-34" Site="ACG-----------------AGTTTACAT" Pvalue="0.00019899999999999999" Start="7" Right="0" regulators="3135491" />
    <regulon_site Name="MCCL_0376:-76" Site="GTTAACTTATATTCAAAATTAGTTTACAA" Pvalue="0.00019899999999999999" Start="4" Right="1" regulators="5666638" />
    <regulon_site Name="SSP2146:-49" Site="GTTAACATATTTGTTATGAAGGTTAACAA" Pvalue="0.00019899999999999999" Start="4" Right="1" regulators="920973" />
    <regulon_site Name="IL1325:-45" Site="AATA----------------ACTTTACAA" Pvalue="0.000216" Start="6" Right="0" regulators="863962" />
    <regulon_site Name="Sden_1657:-43" Site="AACG----------------ACTTGACTA" Pvalue="0.000235" Start="6" Right="0" regulators="6908498" />
    <regulon_site Name="LEUM_0302:-124" Site="TAAC-----------------GGTAACAT" Pvalue="0.00025499999999999996" Start="6" Right="1" regulators="2179849 2180055" />
    <regulon_site Name="NE2300:-96" Site="TTAAT---------------AATTGACAA" Pvalue="0.000277" Start="5" Right="0" regulators="369099" />
    <regulon_site Name="LACR_1953:-98" Site="TAAC-----------------GGTTACTA" Pvalue="0.000277" Start="6" Right="1" regulators="1789226" />
    <regulon_site Name="Sca_2002:-63" Site="GTTAACTATATAAAAAAATAAGTTAACAA" Pvalue="0.0003" Start="4" Right="1" regulators="5567253" />
    <regulon_site Name="OS145_05987:-44" Site="AATT----------------ACTTTACAA" Pvalue="0.000325" Start="6" Right="0" regulators="2704104" />
    <regulon_site Name="L24031:-99" Site="TAAC-----------------GGTTACTG" Pvalue="0.000325" Start="6" Right="1" regulators="78589" />
    <regulon_site Name="STACA0001_0458:-43" Site="GTTAACATATTTATAAATATAGTTTACAT" Pvalue="0.00035099999999999997" Start="4" Right="1" regulators="6431619" />
    <regulon_site Name="Tola_1096:-44" Site="AATC----------------TATTTACAT" Pvalue="0.000379" Start="6" Right="0" regulators="7700874" />
    <regulon_site Name="SA0533:-48" Site="GTTAACAAGATGTATTTTAAAGTTTACAT" Pvalue="0.000379" Start="4" Right="1" regulators="103596" />
    <regulon_site Name="MED297_08751:-83" Site="AAGT----------------AATTGACAA" Pvalue="0.00043999999999999996" Start="6" Right="0" regulators="2774487" />
    <regulon_site Name="Ping_1925:-52" Site="CAACT---------------TCTTTACAT" Pvalue="0.00043999999999999996" Start="5" Right="0" regulators="1972654" />
    <regulon_site Name="CV4381:-132" Site="CAATT---------------GTTTGACAG" Pvalue="0.00043999999999999996" Start="5" Right="0" regulators="515647" />
    <regulon_site Name="SH2418:-55" Site="GTTAACATAATATAAAATAAAGTTAACAT" Pvalue="0.000474" Start="4" Right="1" regulators="918387" />
    <regulon_site Name="OS145_05992:-95" Site="AAGT----------------AATTGACAG" Pvalue="0.000509" Start="6" Right="0" regulators="2704104" />
    <regulon_site Name="LHK_00097:-900" Site="TTATA---------------GTTTGACAG" Pvalue="0.000547" Start="5" Right="0" regulators="7589905" />
    <regulon_site Name="MED297_08746:-231" Site="AATT----------------ACTTTACAT" Pvalue="0.000587" Start="6" Right="0" regulators="2774487" />
    <regulon_site Name="Tbd_0319:-583" Site="CAAT----------------ATTTGACAG" Pvalue="0.000587" Start="6" Right="0" regulators="3415810" />
    <regulon_site Name="PBPRA2330:-36" Site="ATC-----------------GGTTGAAAG" Pvalue="0.00062999999999999992" Start="7" Right="0" regulators="775163" />
    <regulon_site Name="Sca_0740:-367" Site="GTAAACTTAAAAATAAATAAAATTAACAA" Pvalue="0.00062999999999999992" Start="4" Right="1" regulators="5567253" />
    <regulon_site Name="str0674:-35" Site="TAAC-----------------GTTAACTC" Pvalue="0.000674" Start="6" Right="1" regulators="927322" />
    <regulon_site Name="MADE_02212:-18" Site="AACT----------------CCTTTACCA" Pvalue="0.000772" Start="6" Right="0" regulators="6897924" />
    <regulon_site Name="MCCL_0134:-75" Site="GTTAACTTTTTGTACTAAAAGGTTAACGA" Pvalue="0.000772" Start="4" Right="1" regulators="5666638" />
    <regulon_site Name="IL1324:-89" Site="AAGT----------------TATTGACAG" Pvalue="0.000772" Start="6" Right="0" regulators="863962" />
    <regulon_site Name="MB2181_06030:-81" Site="TAAAA---------------GCTTAACCA" Pvalue="0.000824" Start="5" Right="0" regulators="3072798" />
    <regulon_site Name="SSU05_0509:-33" Site="TAAC-----------------GATAACAA" Pvalue="0.000824" Start="6" Right="1" regulators="3592644" />
    <regulon_site Name="BH3358:-33" Site="TTAAC----------------GTAAACAT" Pvalue="0.0019200000000000003" Start="4" Right="0" regulators="64266" />
    <regulon_site Name="Mmol_0571:17" Site="AACA----------------TTTGAACAA" Pvalue="0.00408" Start="6" Right="0" regulators="7670863" />
    <regulon_site Name="LHK_00099:12" Site="CAAAC---------------TATAAACAG" Pvalue="0.0048800000000000007" Start="5" Right="0" regulators="7589905" />
    <regulon_site Name="Tbd_0317:-25" Site="AAAT----------------ATTGAACAT" Pvalue="0.0063000000000000009" Start="6" Right="0" regulators="3415810" />
  </Sites>
  <PWM>
    <ResidueSite Site="0" PWM="0.567857 0.264286 0.075 0.092857" Bits="0.2" />
    <ResidueSite Site="0" PWM="0.65 0.171429 0.007143 0.171429" Bits="0.5" />
    <ResidueSite Site="0" PWM="0.441404 0.109224 0.030054 0.419319" Bits="0.5" />
    <ResidueSite Site="0" PWM="0.281922 0.148897 0.1134 0.455781" Bits="0.2" />
    <ResidueSite Site="0" PWM="0.28456 0.213304 0.134129 0.368008" Bits="0" />
    <ResidueSite Site="0" PWM="0.274315 0.269451 0.19193 0.264304" Bits="0" />
    <ResidueSite Site="0" PWM="0.292172 0.326594 0.19193 0.189304" Bits="0" />
    <ResidueSite Site="0" PWM="0.281457 0.337308 0.19193 0.189304" Bits="0" />
    <ResidueSite Site="0" PWM="0.3136 0.301594 0.195502 0.189304" Bits="0" />
    <ResidueSite Site="0" PWM="0.295743 0.319451 0.19193 0.192875" Bits="0" />
    <ResidueSite Site="0" PWM="0.299315 0.312308 0.19193 0.196447" Bits="0" />
    <ResidueSite Site="0" PWM="0.320743 0.287308 0.202644 0.189304" Bits="0" />
    <ResidueSite Site="0" PWM="0.310029 0.305166 0.195502 0.189304" Bits="0" />
    <ResidueSite Site="0" PWM="0.295743 0.319451 0.19193 0.192875" Bits="0" />
    <ResidueSite Site="0" PWM="0.3136 0.294451 0.195502 0.196447" Bits="0" />
    <ResidueSite Site="0" PWM="0.306457 0.305166 0.19193 0.196447" Bits="0" />
    <ResidueSite Site="0" PWM="0.317172 0.301594 0.19193 0.189304" Bits="0" />
    <ResidueSite Site="0" PWM="0.302886 0.312308 0.195502 0.189304" Bits="0" />
    <ResidueSite Site="0" PWM="0.335029 0.280166 0.19193 0.192875" Bits="0" />
    <ResidueSite Site="0" PWM="0.3386 0.276594 0.195502 0.189304" Bits="0" />
    <ResidueSite Site="0" PWM="0.300863 0.149455 0.419864 0.129818" Bits="0.2" />
    <ResidueSite Site="0" PWM="0.057143 0.017857 0.885714 0.039286" Bits="1.6" />
    <ResidueSite Site="0" PWM="0.003571 0.95 0.042857 0.003571" Bits="1.4" />
    <ResidueSite Site="0" PWM="0.007143 0.985714 0.007143 0" Bits="1.6" />
    <ResidueSite Site="0" PWM="0.164286 0.378571 0.457143 0" Bits="0.5" />
    <ResidueSite Site="0" PWM="1 0 0 0" Bits="1.8" />
    <ResidueSite Site="0" PWM="0.003571 0 0 0.996429" Bits="2.3" />
    <ResidueSite Site="0" PWM="0.8 0.117857 0.046429 0.035714" Bits="0.9" />
    <ResidueSite Site="0" PWM="0.517857 0.182143 0.289286 0.010714" Bits="0.5" />
  </PWM>
</AnnotationModel>